torch_hypothesis/__init__.py
torch_hypothesis-0.2.0.dist-info/WHEEL
torch_hypothesis-0.2.0.dist-info/METADATA
torch_hypothesis-0.2.0.dist-info/RECORD
